ddm/__init__.py
ddm/plot.py
pyddm/__init__.py
pyddm/_version.py
pyddm/analytic.py
pyddm/csolve.cpython-314-x86_64-linux-gnu.so
pyddm/fitresult.py
pyddm/functions.py
pyddm/logger.py
pyddm/model.py
pyddm/parameters.py
pyddm/plot.py
pyddm/sample.py
pyddm/solution.py
pyddm/tridiag.py
pyddm/models/__init__.py
pyddm/models/base.py
pyddm/models/bound.py
pyddm/models/drift.py
pyddm/models/ic.py
pyddm/models/loss.py
pyddm/models/noise.py
pyddm/models/overlay.py
pyddm/models/paranoid_types.py
pyddm-0.9.0.dist-info/METADATA
pyddm-0.9.0.dist-info/WHEEL
pyddm-0.9.0.dist-info/top_level.txt
pyddm-0.9.0.dist-info/RECORD
pyddm-0.9.0.dist-info/licenses/LICENSE.txt
