Metadata-Version: 2.1
Name: pyddm
Version: 0.9.0
Summary: Generalized drift diffusion modeling for Python
Home-page: https://github.com/mwshinn/PyDDM
Author: Max Shinn, Norman Lam
Author-email: m.shinn@ucl.ac.uk
Maintainer: Max Shinn
Maintainer-email: m.shinn@ucl.ac.uk
License: MIT
Classifier: Development Status :: 4 - Beta
Classifier: Intended Audience :: Science/Research
Classifier: License :: OSI Approved :: MIT License
Classifier: Programming Language :: Python :: 3
Classifier: Topic :: Education :: Testing
Classifier: Topic :: Scientific/Engineering
Classifier: Topic :: Scientific/Engineering :: Physics
Classifier: Topic :: Scientific/Engineering :: Medical Science Apps.
Classifier: Topic :: Scientific/Engineering :: Bio-Informatics
Requires-Python: >=3.6
License-File: LICENSE.txt
Requires-Dist: numpy >=1.9.2
Requires-Dist: scipy >=0.16
Requires-Dist: matplotlib
Requires-Dist: paranoid-scientist >=0.2.3
Requires-Dist: pandas
